Workbook

Sheet Project
A1: TAKEOFF DESK: ESTIMATE
A2: Orange cells are inputs. Everything else calculates.
A4: Client (subcontractor)
A5: Project name
A6: Project address
A7: GC / bidding to
A8: Bid due date
A9: Drawing set / date
A10: Addenda included | B10: None
A11: Gross building area (SF) | B11: 0
A12: Overhead % | B12: 0.1
A13: Profit % | B13: 0.1
A14: Sales tax on material % | B14: 0
A15: Estimator
A16: Checked by (QC)

Sheet Summary
A1: BID SUMMARY
A3: Material subtotal | B3: =SUM(Takeoff!K2:K201)
A4: Sales tax on material | B4: =B3*Project!B14
A5: Labor subtotal | B5: =SUM(Takeoff!L2:L201)
A6: Direct cost | B6: =B3+B4+B5
A7: Overhead | B7: =B6*Project!B12
A8: Profit | B8: =(B6+B7)*Project!B13
A9: BID TOTAL | B9: =B6+B7+B8
A11: Gross building area (SF) | B11: =Project!B11
A12: Bid $ per SF | B12: =IF(B11>0,B9/B11,"enter area")
A13: Material / labor split | B13: =IF(B6>0,TEXT(B3/B6,"0%")&" / "&TEXT(B5/B6,"0%"),"")
A15: QC: compare Bid $/SF to past jobs of the same type. A result far off your normal range usually means a missed area or a scale error.

Sheet Takeoff
A1: Code | B1: Description | C1: Location / area | D1: Drawing ref | E1: Qty | F1: Unit | G1: Waste % | H1: Qty w/ waste | I1: Material $/unit | J1: Labor $/unit | K1: Material $ | L1: Labor $ | M1: Line total | N1: Notes
A2: 09-21A | B2: 5/8" Type X GWB, both sides, Type A walls | C2: Level 1 | D2: A-101 | E2: 0 | F2: SF | G2: 0.1 | H2: =IF(E2="","",E2*(1+G2)) | K2: =IF(E2="","",H2*I2) | L2: =IF(E2="","",E2*J2) | M2: =IF(E2="","",K2+L2)
A3: 09-22A | B3: 3-5/8" 20ga studs @ 16" o.c. | C3: Level 1 | D3: A-101 | E3: 0 | F3: LF | G3: 0.05 | H3: =IF(E3="","",E3*(1+G3)) | K3: =IF(E3="","",H3*I3) | L3: =IF(E3="","",E3*J3) | M3: =IF(E3="","",K3+L3)
A4: 09-51A | B4: ACT ceiling 2x4 | C4: Level 1 | D4: A-121 | E4: 0 | F4: SF | G4: 0.05 | H4: =IF(E4="","",E4*(1+G4)) | K4: =IF(E4="","",H4*I4) | L4: =IF(E4="","",E4*J4) | M4: =IF(E4="","",K4+L4)
A5: 09-29A | B5: Level 5 finish | C5: Level 1 | D5: A-101 | E5: 0 | F5: SF | G5: 0 | H5: =IF(E5="","",E5*(1+G5)) | K5: =IF(E5="","",H5*I5) | L5: =IF(E5="","",E5*J5) | M5: =IF(E5="","",K5+L5)
H6: =IF(E6="","",E6*(1+G6)) | K6: =IF(E6="","",H6*I6) | L6: =IF(E6="","",E6*J6) | M6: =IF(E6="","",K6+L6)
H7: =IF(E7="","",E7*(1+G7)) | K7: =IF(E7="","",H7*I7) | L7: =IF(E7="","",E7*J7) | M7: =IF(E7="","",K7+L7)
H8: =IF(E8="","",E8*(1+G8)) | K8: =IF(E8="","",H8*I8) | L8: =IF(E8="","",E8*J8) | M8: =IF(E8="","",K8+L8)
H9: =IF(E9="","",E9*(1+G9)) | K9: =IF(E9="","",H9*I9) | L9: =IF(E9="","",E9*J9) | M9: =IF(E9="","",K9+L9)
H10: =IF(E10="","",E10*(1+G10)) | K10: =IF(E10="","",H10*I10) | L10: =IF(E10="","",E10*J10) | M10: =IF(E10="","",K10+L10)
H11: =IF(E11="","",E11*(1+G11)) | K11: =IF(E11="","",H11*I11) | L11: =IF(E11="","",E11*J11) | M11: =IF(E11="","",K11+L11)
H12: =IF(E12="","",E12*(1+G12)) | K12: =IF(E12="","",H12*I12) | L12: =IF(E12="","",E12*J12) | M12: =IF(E12="","",K12+L12)
H13: =IF(E13="","",E13*(1+G13)) | K13: =IF(E13="","",H13*I13) | L13: =IF(E13="","",E13*J13) | M13: =IF(E13="","",K13+L13)
H14: =IF(E14="","",E14*(1+G14)) | K14: =IF(E14="","",H14*I14) | L14: =IF(E14="","",E14*J14) | M14: =IF(E14="","",K14+L14)
H15: =IF(E15="","",E15*(1+G15)) | K15: =IF(E15="","",H15*I15) | L15: =IF(E15="","",E15*J15) | M15: =IF(E15="","",K15+L15)
H16: =IF(E16="","",E16*(1+G16)) | K16: =IF(E16="","",H16*I16) | L16: =IF(E16="","",E16*J16) | M16: =IF(E16="","",K16+L16)
H17: =IF(E17="","",E17*(1+G17)) | K17: =IF(E17="","",H17*I17) | L17: =IF(E17="","",E17*J17) | M17: =IF(E17="","",K17+L17)
... H201: =IF(E201="","",E201*(1+G201)) | K201: =IF(E201="","",H201*I201) | L201: =IF(E201="","",E201*J201) | M201: =IF(E201="","",K201+L201)
